malcube/__init__.py
malcube/cli.py
malcube/logo.py
malcube/main.py
malcube-0.0.2.dist-info/LICENSE
malcube-0.0.2.dist-info/METADATA
malcube-0.0.2.dist-info/WHEEL
malcube-0.0.2.dist-info/entry_points.txt
malcube-0.0.2.dist-info/top_level.txt
malcube-0.0.2.dist-info/RECORD
