Metadata-Version: 2.1
Name: malcube
Version: 0.0.2
Summary: Next-generation reverse engineering engine and threat intelligence analyzer
Home-page: https://github.com/malcube/malcube
Author: JunWei Song
Author-email: sungboss2004@gmail.com
License: UNKNOWN
Platform: UNKNOWN
Classifier: Programming Language :: Python :: 3
Classifier: License :: OSI Approved :: GNU General Public License v3 (GPLv3)
Classifier: Operating System :: OS Independent
Classifier: Topic :: Security
Requires-Python: >=3.9
License-File: LICENSE
Requires-Dist: pefile
Requires-Dist: pyelftools
Requires-Dist: click
